MakeDjango/MakeDjango.py
MakeDjango/__init__.py
MakeDjango/core/__init__.py
MakeDjango/core/auto_make.py
MakeDjango/core/custom_make.py
MakeDjango/core/linux.sh
MakeDjango/core/processor.py
MakeDjango/core/venv_make.py
MakeDjango/core/win32.bat
MakeDjango/template/Dockerfile
MakeDjango/template/__init__.py
MakeDjango/template/admin.py
MakeDjango/template/asgi.py
MakeDjango/template/authentications.py
MakeDjango/template/consumers.py
MakeDjango/template/docker-compose.yaml
MakeDjango/template/forms.py
MakeDjango/template/manage.py
MakeDjango/template/managers.py
MakeDjango/template/middlewares.py
MakeDjango/template/models.py
MakeDjango/template/permissions.py
MakeDjango/template/querysets.py
MakeDjango/template/routers.py
MakeDjango/template/schema.py
MakeDjango/template/serializers.py
MakeDjango/template/settings.py
MakeDjango/template/signals.py
MakeDjango/template/tests.py
MakeDjango/template/throttles.py
MakeDjango/template/urls.py
MakeDjango/template/utils.py
MakeDjango/template/views.py
MakeDjango/template/wsgi.py
MakeDjango-1.2.6.dist-info/LICENSE
MakeDjango-1.2.6.dist-info/METADATA
MakeDjango-1.2.6.dist-info/WHEEL
MakeDjango-1.2.6.dist-info/entry_points.txt
MakeDjango-1.2.6.dist-info/top_level.txt
MakeDjango-1.2.6.dist-info/RECORD
