Metadata-Version: 2.1
Name: MakeDjango
Version: 1.2.6
Summary: simple command line tool for start project
Home-page: https://github.com/MahanBi/MakeDjango.git
Author: Mahan Bakhshi
Author-email: dirtymbgamer@gmail.com
Maintainer: Mahan Bakhshi
Maintainer-email: dirtymbgamer@gmail.com
License: MIT
Project-URL: issues, https://github.com/MahanBi/MakeDjango/issues
Platform: UNKNOWN
Classifier: Programming Language :: Python :: 3
Classifier: License :: OSI Approved :: MIT License
Classifier: Operating System :: OS Independent
Requires-Python: >=3.8
License-File: LICENSE
Requires-Dist: setuptools
Requires-Dist: wheel
Requires-Dist: asgiref (==3.4.1)
Requires-Dist: pytz (==2021.3)
Requires-Dist: prompt-toolkit (==1.0.14)
Requires-Dist: pyfiglet (==0.8.post1)
Requires-Dist: PyInquirer (==1.0.3)
